AUTHORS.rst
CONTRIBUTING.rst
HISTORY.rst
LICENSE
MANIFEST.in
README.rst
setup.cfg
setup.py
cacheq/__init__.py
cacheq/base.py
cacheq/models.py
cacheq/utils.py
cacheq/management/__init__.py
cacheq/management/commands/__init__.py
cacheq/management/commands/cqclear.py
cacheq/management/commands/cqworker.py
django_cacheq.egg-info/PKG-INFO
django_cacheq.egg-info/SOURCES.txt
django_cacheq.egg-info/dependency_links.txt
django_cacheq.egg-info/not-zip-safe
django_cacheq.egg-info/pbr.json
django_cacheq.egg-info/top_level.txt