Metadata-Version: 1.1
Name: django-cacheq
Version: 0.1.1
Summary: Background tasks using django's cache framework.
Home-page: https://github.com/misterte/django-cacheq
Author: Andrés Bucchi
Author-email: afbucchi@gmail.com
License: BSD
Keywords: django-cacheq
Platform: UNKNOWN
Classifier: Development Status :: 2 - Pre-Alpha
Classifier: Framework :: Django
Classifier: Intended Audience :: Developers
Classifier: License :: OSI Approved :: BSD License
Classifier: Natural Language :: English
Classifier: Programming Language :: Python :: 2
Classifier: Programming Language :: Python :: 2.6
Classifier: Programming Language :: Python :: 2.7
Classifier: Programming Language :: Python :: 3
Classifier: Programming Language :: Python :: 3.3
